windows_path/__init__.py
windows_path/__main__.py
windows_path/cli.py
windows_path/path_manager.py
windows_path-0.1.0.dist-info/LICENSE
windows_path-0.1.0.dist-info/METADATA
windows_path-0.1.0.dist-info/WHEEL
windows_path-0.1.0.dist-info/entry_points.txt
windows_path-0.1.0.dist-info/top_level.txt
windows_path-0.1.0.dist-info/RECORD
