Metadata-Version: 2.1
Name: windows_path
Version: 0.1.0
Summary: Manage the Windows user PATH environment variable from Python or the command line.
Author-email: azwri <azwri@example.com>
Project-URL: Homepage, https://github.com/azwri/windows_path
Project-URL: Repository, https://github.com/azwri/windows_path
Project-URL: Issues, https://github.com/azwri/windows_path/issues
Keywords: windows,path,environment,cli
Classifier: Programming Language :: Python :: 3
Classifier: Programming Language :: Python :: 3 :: Only
Classifier: Programming Language :: Python :: 3.6
Classifier: Programming Language :: Python :: 3.7
Classifier: Programming Language :: Python :: 3.8
Classifier: Programming Language :: Python :: 3.9
Classifier: Programming Language :: Python :: 3.10
Classifier: Programming Language :: Python :: 3.11
Classifier: Environment :: Console
Classifier: Operating System :: Microsoft :: Windows
Classifier: Topic :: System :: Systems Administration
Classifier: Intended Audience :: System Administrators
Classifier: License :: OSI Approved :: MIT License
Requires-Python: >=3.6
License-File: LICENSE
